{"avatar": "https://images.chesscomfiles.com/uploads/v1/user/76786362.8b9d7e63.200x200o.76fc600d72a4.jpg", "player_id": 76786362, "@id": "https://api.chess.com/pub/player/gausal", "url": "https://www.chess.com/member/GAusal", "name": "Jorge Carlos Antonio", "username": "gausal", "title": "FM", "followers": 393, "country": "https://api.chess.com/pub/country/AR", "location": "Buenos Aires", "last_online": 1777319265, "joined": 1586964216, "status": "premium", "is_streamer": false, "verified": false, "league": "Champion", "streaming_platforms": []}