{"avatar": "https://images.chesscomfiles.com/uploads/v1/user/24528170.b4b587e6.200x200o.840eb56debed.jpeg", "player_id": 24528170, "@id": "https://api.chess.com/pub/player/dawidczerw", "url": "https://www.chess.com/member/DawidCzerw", "name": "Dawid Czerw", "username": "dawidczerw", "title": "IM", "followers": 5849, "country": "https://api.chess.com/pub/country/PL", "location": "Lublin", "last_online": 1781271844, "joined": 1444579154, "status": "staff", "is_streamer": true, "twitch_url": "https://twitch.tv/dawidczerw", "verified": false, "league": "Legend", "streaming_platforms": [{"type": "twitch", "channel_url": "https://twitch.tv/dawidczerw"}]}