{"avatar": "https://images.chesscomfiles.com/uploads/v1/user/18158666.f27f6748.200x200o.94609790fa92.png", "player_id": 18158666, "@id": "https://api.chess.com/pub/player/robram", "url": "https://www.chess.com/member/RobRam", "name": "Robert Ramirez", "username": "robram", "title": "NM", "followers": 7618, "country": "https://api.chess.com/pub/country/US", "location": "Miami, Florida", "last_online": 1781239152, "joined": 1405906613, "status": "premium", "is_streamer": false, "verified": false, "league": "Champion", "streaming_platforms": []}