{"chess_daily": {"last": {"rating": 398, "date": 1704649426, "rd": 347}, "record": {"win": 0, "loss": 2, "draw": 0, "time_per_move": 18117, "timeout_percent": 0}}, "chess_rapid": {"last": {"rating": 2298, "date": 1761160522, "rd": 50}, "best": {"rating": 2446, "date": 1668376032, "game": "https://www.chess.com/game/live/62114321243"}, "record": {"win": 4, "loss": 1, "draw": 1}}, "chess_bullet": {"last": {"rating": 2473, "date": 1781459829, "rd": 66}, "best": {"rating": 2473, "date": 1781459829, "game": "https://www.chess.com/game/live/170087804780"}, "record": {"win": 177, "loss": 63, "draw": 5}}, "chess_blitz": {"last": {"rating": 2523, "date": 1781470530, "rd": 42}, "best": {"rating": 2559, "date": 1774370686, "game": "https://www.chess.com/game/live/159611244989"}, "record": {"win": 677, "loss": 374, "draw": 76}}, "tactics": {"highest": {"rating": 2415, "date": 1768749440}, "lowest": {"rating": 2227, "date": 1759000557}}, "puzzle_rush": {"best": {"total_attempts": 61, "score": 58}}}