{"avatar": "https://images.chesscomfiles.com/uploads/v1/user/13032778.34ea149b.200x200o.94178c2253f3.png", "player_id": 13032778, "@id": "https://api.chess.com/pub/player/nowinchess", "url": "https://www.chess.com/member/NowInChess", "name": "Gerardo Fernandez", "username": "nowinchess", "title": "CM", "followers": 62, "country": "https://api.chess.com/pub/country/XB", "last_online": 1781472724, "joined": 1375738810, "status": "premium", "is_streamer": false, "verified": false, "league": "Elite", "streaming_platforms": []}