{"avatar": "https://images.chesscomfiles.com/uploads/v1/user/41634408.174c26d5.200x200o.0c99232069df.png", "player_id": 41634408, "@id": "https://api.chess.com/pub/player/didici", "url": "https://www.chess.com/member/Didici", "name": "Lorenzo Lodici", "username": "didici", "title": "GM", "followers": 413, "country": "https://api.chess.com/pub/country/IT", "last_online": 1781458966, "joined": 1514128397, "status": "premium", "is_streamer": false, "verified": false, "league": "Champion", "streaming_platforms": []}