{"avatar": "https://images.chesscomfiles.com/uploads/v1/user/380039297.f55762a6.200x200o.181e8f088f01.png", "player_id": 380039297, "@id": "https://api.chess.com/pub/player/miguel-la", "url": "https://www.chess.com/member/Miguel-LA", "name": "Miguel L\u00e1zaro Azcutia", "username": "miguel-la", "title": "CM", "followers": 4, "country": "https://api.chess.com/pub/country/ES", "last_online": 1780309440, "joined": 1723218583, "status": "premium", "is_streamer": false, "verified": false, "league": "Crystal", "streaming_platforms": []}