{"chess_daily": {"last": {"rating": 1604, "date": 1780341260, "rd": 95}, "best": {"rating": 1891, "date": 1777434621, "game": "https://www.chess.com/game/daily/963178023"}, "record": {"win": 36, "loss": 9, "draw": 1, "time_per_move": 23683, "timeout_percent": 33}, "tournament": {"points": 0, "withdraw": 0, "count": 1, "highest_finish": 0}}, "chess_rapid": {"last": {"rating": 2387, "date": 1780163996, "rd": 49}, "best": {"rating": 2610, "date": 1702905318, "game": "https://www.chess.com/game/live/96644232111"}, "record": {"win": 4, "loss": 3, "draw": 0}}, "chess_bullet": {"last": {"rating": 2627, "date": 1780935039, "rd": 46}, "best": {"rating": 2714, "date": 1702907808, "game": "https://www.chess.com/game/live/96646160145"}, "record": {"win": 109, "loss": 55, "draw": 5}}, "chess_blitz": {"last": {"rating": 2872, "date": 1781454834, "rd": 31}, "best": {"rating": 2925, "date": 1780932556, "game": "https://www.chess.com/game/live/170129832074"}, "record": {"win": 660, "loss": 675, "draw": 80}}, "tactics": {"highest": {"rating": 2821, "date": 1777104624}, "lowest": {"rating": 2314, "date": 1756460390}}, "puzzle_rush": {"best": {"total_attempts": 67, "score": 64}}}