{"avatar": "https://images.chesscomfiles.com/uploads/v1/user/49863952.99486387.200x200o.eae7ab7a8f5a.jpg", "player_id": 49863952, "@id": "https://api.chess.com/pub/player/rostovmaxim", "url": "https://www.chess.com/member/rostovmaxim", "name": "Maxim Borisov", "username": "rostovmaxim", "title": "CM", "followers": 20, "country": "https://api.chess.com/pub/country/JP", "location": "Rostov-on-Don", "last_online": 1781481091, "joined": 1537274457, "status": "premium", "is_streamer": false, "verified": false, "league": "Elite", "streaming_platforms": []}