{"avatar": "https://images.chesscomfiles.com/uploads/v1/user/76153194.4a18de6b.200x200o.eae8abe13fdd.gif", "player_id": 76153194, "@id": "https://api.chess.com/pub/player/mitul", "url": "https://www.chess.com/member/Mitul", "name": "Mitul K H", "username": "mitul", "title": "CM", "followers": 746, "country": "https://api.chess.com/pub/country/IN", "last_online": 1781289980, "joined": 1586439965, "status": "premium", "is_streamer": false, "verified": false, "league": "Legend", "streaming_platforms": []}