{"chess_rapid": {"last": {"rating": 2437, "date": 1706286806, "rd": 72}, "best": {"rating": 2600, "date": 1676322142, "game": "https://www.chess.com/game/live/70060078159"}, "record": {"win": 19, "loss": 18, "draw": 7}}, "chess_bullet": {"last": {"rating": 2687, "date": 1769888917, "rd": 47}, "best": {"rating": 2798, "date": 1642506019, "game": "https://www.chess.com/game/live/98910964109"}, "record": {"win": 1995, "loss": 1390, "draw": 200}}, "chess_blitz": {"last": {"rating": 2841, "date": 1781295257, "rd": 21}, "best": {"rating": 3014, "date": 1777565137, "game": "https://www.chess.com/game/live/151744085797"}, "record": {"win": 31164, "loss": 24812, "draw": 4902}}, "tactics": {"highest": {"rating": 2479, "date": 1477635594}, "lowest": {"rating": 2479, "date": 1477635594}}, "puzzle_rush": {"best": {"total_attempts": 46, "score": 43}}}