{"avatar": "https://images.chesscomfiles.com/uploads/v1/user/74474022.cbcec87b.200x200o.30bf4c8a36dc.jpeg", "player_id": 74474022, "@id": "https://api.chess.com/pub/player/elprofessor21", "url": "https://www.chess.com/member/Elprofessor21", "name": "Christos Krallis", "username": "elprofessor21", "title": "IM", "followers": 11, "country": "https://api.chess.com/pub/country/GR", "last_online": 1781042385, "joined": 1585148516, "status": "premium", "is_streamer": false, "verified": false, "league": "Champion", "streaming_platforms": []}