{"groups": ["https://api.chess.com/pub/tournament/titled-tuesday-blitz-march-17-2026-6282783/3/1"], "players": [{"username": "hikaru"}, {"username": "reader777"}, {"username": "denlaz"}, {"username": "moro182"}, {"username": "sina-movahed"}, {"username": "romik2012"}, {"username": "lyonbeast"}, {"username": "ckgchess"}, {"username": "alen_chessmate"}, {"username": "fairchess_on_youtube"}, {"username": "trahtarbelarus"}, {"username": "alexrustemov"}, {"username": "alexpapasimakopoulos"}, {"username": "faustinooro"}, {"username": "timaina"}, {"username": "oleksandr_bortnyk"}, {"username": "denizdirikolu09"}, {"username": "msb2"}, {"username": "wqws"}, {"username": "gmbenjaminbok"}, {"username": "levonaronian"}, {"username": "tikhon_popov"}, {"username": "polish_fighter3000"}, {"username": "alexboy14"}, {"username": "gianmarco_es"}, {"username": "andreikka"}, {"username": "ascender21"}, {"username": "bogdandeac"}, {"username": "allcer7"}, {"username": "only_strong_moves"}, {"username": "arseniy_nesterov"}, {"username": "sanan_sjugirov"}, {"username": "szparu"}, {"username": "aa175"}, {"username": "scarabee43"}, {"username": "grandelicious"}, {"username": "blitzking1729"}, {"username": "igor_janik"}, {"username": "beca95"}, {"username": "durarbayli"}, {"username": "gabber2011"}, {"username": "rezamahdavi2008"}, {"username": "acidshazz"}, {"username": "ga_r"}, {"username": "sergoy"}, {"username": "eagle_2019"}, {"username": "vaathi_coming"}, {"username": "lion-al-messi"}, {"username": "liontheleon_06"}, {"username": "dixit_nikhil"}, {"username": "fh2411"}, {"username": "vishwa_vijeta"}, {"username": "mokshad1603"}, {"username": "domyk16"}, {"username": "nodariousbig"}, {"username": "slidingknight2775"}, {"username": "sahist07"}, {"username": "aygehovit1992"}, {"username": "mishanick"}, {"username": "parhamov"}, {"username": "jefferyx"}, {"username": "egehany09"}, {"username": "chessfighter_2011"}, {"username": "boutikaki"}, {"username": "niklasschmider"}, {"username": "bescmelasti"}, {"username": "tsaruk_maks"}, {"username": "slovak_fighter2000"}, {"username": "dangerousboy228"}, {"username": "bencus12"}, {"username": "patmat123456"}, {"username": "guillembaches"}, {"username": "witik"}, {"username": "yan_dyomin2010"}, {"username": "shahmatkanal"}, {"username": "tryhardissues"}, {"username": "ural58"}, {"username": "nikolas1408"}, {"username": "levqcq"}, {"username": "dreamsarefake"}, {"username": "asvz"}, {"username": "gelmanalexander"}, {"username": "guillead1"}, {"username": "vesper2018"}, {"username": "chessqueen"}, {"username": "mazarini41"}, {"username": "davvittttt2009"}, {"username": "wise_guyyy"}, {"username": "aaravdenglaofficial"}, {"username": "agw2016"}, {"username": "betta2004"}, {"username": "zachhkl"}, {"username": "mikakarttunen"}, {"username": "koshkamatrioshka"}, {"username": "dinamo81"}, {"username": "agustinwyatt"}, {"username": "ant_chess_2019"}, {"username": "gueraumasague"}, {"username": "aljoschafeuerstack"}, {"username": "janmur7"}, {"username": "shivananda1964"}, {"username": "jddg"}, {"username": "gm_huschenbeth"}, {"username": "mokerslag"}, {"username": "dannyings83972"}, {"username": "cartonmaster"}, {"username": "teresin05"}, {"username": "mr-uteligger"}, {"username": "cocosiukas"}, {"username": "petrgnojek"}, {"username": "julian2024"}, {"username": "randomnoob04"}, {"username": "grishap06"}, {"username": "zhoh_off"}, {"username": "tim1234321"}, {"username": "lerry0525"}, {"username": "kingofchesss17"}, {"username": "sunaya1"}, {"username": "agoking701"}, {"username": "pesandu_liyanage_1"}, {"username": "lady_nika"}, {"username": "matols"}, {"username": "shuvalov"}, {"username": "davidlana1987"}, {"username": "rachidhuilda"}, {"username": "plpipih-tesrme"}, {"username": "theinfinity011"}, {"username": "bazar-wokzal"}, {"username": "pavle896"}, {"username": "maurinm"}, {"username": "aisen1011"}, {"username": "gangsterrito"}, {"username": "levkotelva"}, {"username": "egk_06"}, {"username": "zoktayyyyfanclubbb"}, {"username": "b_griffin"}, {"username": "jens1102"}, {"username": "hilleltoledo"}, {"username": "witty_alien"}, {"username": "idobenartzi"}, {"username": "judomaster3"}, {"username": "johncenathegoat1"}, {"username": "maus7"}, {"username": "nowinchess"}, {"username": "sergioocampos"}, {"username": "taglit"}, {"username": "reinisuz"}, {"username": "cabezauro"}, {"username": "jan2404"}, {"username": "dishal2010"}, {"username": "bigmanevan"}, {"username": "dawidczerw"}, {"username": "nutsontheboard"}, {"username": "mikesailer"}, {"username": "x-6605293955"}, {"username": "aural1011"}, {"username": "kaidanov"}, {"username": "bodhiknight"}, {"username": "volcanator"}, {"username": "aguiar94"}, {"username": "mind-virus"}, {"username": "dinosavr75"}, {"username": "pirulillo"}, {"username": "gorindeshi"}, {"username": "cristianchess19"}, {"username": "kr1sjan1s_la2ars"}, {"username": "smiechu"}, {"username": "stormstrategist"}, {"username": "saikrishnareturns"}, {"username": "gau248"}, {"username": "homealone20"}, {"username": "manitodeplomo"}, {"username": "arnaking20"}, {"username": "m_ezat"}, {"username": "wildjoker2016"}, {"username": "arseny-kleschevnikov"}, {"username": "gmr7525"}, {"username": "championnn-9"}, {"username": "sanbruh"}, {"username": "rhwr"}, {"username": "angamat"}, {"username": "gh6999"}, {"username": "nmchesstoimpress"}, {"username": "maxleto"}, {"username": "meotintin"}, {"username": "recombinant"}, {"username": "yushko_olga"}, {"username": "kielinkei"}, {"username": "quetia_pin"}, {"username": "alexlongson"}, {"username": "luca_va99"}, {"username": "tol_tol"}, {"username": "aamuktha-guntaka"}, {"username": "ivandrade10"}, {"username": "vmulay"}, {"username": "cheer_down"}, {"username": "amardeepb"}, {"username": "saihanthiha"}, {"username": "louis-paulsen-fan"}, {"username": "fighter0411"}, {"username": "angeldelasoledad"}, {"username": "sofiia_hryzlova"}, {"username": "allespatzer"}, {"username": "aps"}, {"username": "tiagomangialardo"}, {"username": "kuwaitigm"}, {"username": "jaroslavsobek"}, {"username": "kotofeyca"}, {"username": "herminiah"}, {"username": "mcwzpk"}, {"username": "loverischess"}, {"username": "baratheont"}, {"username": "juraj_oruzinsky"}, {"username": "sevilplayschess"}, {"username": "liondinamic"}, {"username": "andrzej"}, {"username": "sunstorm0720"}, {"username": "mastercheese379"}, {"username": "tunartank"}, {"username": "nihalsarin"}, {"username": "ohanyaneminchess"}, {"username": "konavets"}, {"username": "bardiya06"}, {"username": "ghandeevam2003"}, {"username": "ilanschnaider"}, {"username": "fabianocaruana"}, {"username": "hansontwitch"}, {"username": "darkalekhine"}, {"username": "gmwso"}, {"username": "nikotheodorou"}, {"username": "jospem"}, {"username": "iwanyu"}, {"username": "vi_pranav"}, {"username": "superchess02"}, {"username": "artooon"}, {"username": "igorvershinin2009"}, {"username": "volodar_murzin"}, {"username": "zurability"}, {"username": "vovachesss"}, {"username": "njal28"}, {"username": "gabrielian_artur"}, {"username": "crescentmoon2411"}, {"username": "oparingrigoriy"}, {"username": "flawless_fighter"}, {"username": "shimastream"}, {"username": "chessdjw"}, {"username": "shield12"}, {"username": "wonderfultime"}, {"username": "tagir45"}, {"username": "stassb"}, {"username": "savva_krasavva"}, {"username": "aquarium76"}, {"username": "m_pank_537"}, {"username": "viraldus"}, {"username": "gmkrikor"}, {"username": "georgmeier"}, {"username": "manmish2"}, {"username": "speshka"}, {"username": "kirill_klukin"}, {"username": "gaidym72"}, {"username": "hvillagra"}, {"username": "chesswind85"}, {"username": "kildepiotr"}, {"username": "boundless_strike"}, {"username": "hasangatin_ramil"}, {"username": "shubinkirill2003"}, {"username": "mw86"}, {"username": "rasmussvane"}, {"username": "eljanov"}, {"username": "qsjtgx"}, {"username": "byniolus"}, {"username": "tacticthunder"}, {"username": "b_nn_t"}, {"username": "andriidiachek"}, {"username": "robertojbm"}, {"username": "heritiana_andria"}, {"username": "lukaslebakken"}, {"username": "bulgakdamir"}, {"username": "briesmas"}, {"username": "amintabatabaei"}, {"username": "goodoldbell"}, {"username": "fghsmn"}, {"username": "ilqar_74"}, {"username": "jakhongir-vakhidov"}, {"username": "liusia"}, {"username": "yosephtaher"}, {"username": "kosak12"}, {"username": "matthewg-p4p"}, {"username": "ykow2"}, {"username": "ganiev_artur11"}, {"username": "let_it_be_1"}, {"username": "juan-jose-taylor-rodrigue"}, {"username": "newbornnow"}, {"username": "artemdyachuk"}, {"username": "imrosen"}, {"username": "leonid_starozhilov"}, {"username": "polishforce3000"}, {"username": "nexoknight11"}, {"username": "nguyenquanganh3112"}, {"username": "immjam"}, {"username": "germanovs_georgijs"}, {"username": "meri-arabidze"}, {"username": "xilacorigami"}, {"username": "antoni_radzimski"}, {"username": "gmg"}, {"username": "jaisankars"}, {"username": "chesswithakeem"}, {"username": "futurechamp1907"}, {"username": "nikitashandrygin"}, {"username": "individoom"}, {"username": "samdanov"}, {"username": "timurdzhaan"}, {"username": "kasparicy"}, {"username": "iljiushenok_ilya"}, {"username": "hephaestus_11"}, {"username": "mikhal867"}, {"username": "alexei_gubajdullin"}, {"username": "aradhya2000"}, {"username": "elprofessor21"}, {"username": "janistantv"}, {"username": "joliyroger"}, {"username": "bulletteemo"}, {"username": "mcqueen444"}, {"username": "robert_sava"}, {"username": "therabbit19"}, {"username": "laiditmang05_ducminh"}, {"username": "fan_of_chess1908"}, {"username": "leoalonso"}, {"username": "antosha_chekhonte"}, {"username": "adnan_habib"}, {"username": "giomar27"}, {"username": "axolotl_2015"}, {"username": "averagefm"}, {"username": "wildontwitch"}, {"username": "d6stronk"}, {"username": "konradrutkowski"}, {"username": "thebeast2900"}, {"username": "gray_3024"}, {"username": "vinjarhammari"}, {"username": "andrew-blr"}, {"username": "colincreeveydennic"}, {"username": "drkiller67"}, {"username": "karinachess1"}, {"username": "bryantman2014"}, {"username": "gambitgiesbergen"}, {"username": "reymannnathan"}, {"username": "bacus79"}, {"username": "oleksandrprokhorov"}, {"username": "anasta10"}, {"username": "richidelcerro"}, {"username": "zverr1"}, {"username": "zuko07"}, {"username": "yigitk_10"}, {"username": "gennady_kozlov"}, {"username": "srawberryfields"}, {"username": "safikiet"}, {"username": "gryffindorac8"}, {"username": "coachrjm"}, {"username": "iskusnyh"}, {"username": "georgiossouleidis"}, {"username": "albadelomass"}, {"username": "vladislav_voitovich"}, {"username": "yyaroslavchess2010"}, {"username": "dosto07"}, {"username": "pournami_s"}, {"username": "wotgenie"}, {"username": "niilo1"}, {"username": "chessbard1972"}, {"username": "chhunnubabu"}, {"username": "robertskytte"}, {"username": "pizzalover2502"}, {"username": "movingmeats"}, {"username": "jazz_0607"}, {"username": "miterryble"}, {"username": "venemycin"}, {"username": "godzillator"}, {"username": "mnatsakanyan-aren2012"}, {"username": "manukyan_artak"}, {"username": "vladgoncharov"}, {"username": "kononenkod"}, {"username": "wgraif"}, {"username": "giovannibrandao7"}, {"username": "thewinninguy"}, {"username": "paintrain08"}, {"username": "godavarikid"}, {"username": "francesatop"}, {"username": "timur_nurzhanov"}, {"username": "onslowchess"}, {"username": "logicbaba"}, {"username": "endgamedestroyer"}, {"username": "jhc20110307"}, {"username": "kasandra124"}, {"username": "khaled_seyam_2012"}, {"username": "yohankrokov"}, {"username": "borasavran35"}, {"username": "tugaychess"}, {"username": "elpeordelosmejores"}, {"username": "drwonderkid"}, {"username": "sharapovevgeny"}, {"username": "alainbruxelles"}, {"username": "niviattack"}, {"username": "knightinshiningarmour16"}, {"username": "cm_charmander"}, {"username": "life-of-fire"}, {"username": "leowin2012"}, {"username": "zhans_2014"}, {"username": "shanyrak"}, {"username": "luisfsiles"}, {"username": "waly48ks"}, {"username": "rjmcl1"}, {"username": "danifv"}, {"username": "n_i_chess"}, {"username": "chessmarkod"}, {"username": "cheessmasteer54"}, {"username": "sargissyansargis"}, {"username": "hannahsaycestreams"}, {"username": "supergiuly"}, {"username": "supelyel"}, {"username": "lucena125"}, {"username": "mise2020"}, {"username": "annacramling"}, {"username": "khromkin"}, {"username": "diamonds13"}, {"username": "jcmesafischer"}, {"username": "amylazy"}, {"username": "navyblue1"}, {"username": "gen-gutman"}, {"username": "premierchess64"}, {"username": "eugenefurman"}, {"username": "jesper_kjaergaard-jensen"}, {"username": "shirovin"}, {"username": "hunting_lion14"}, {"username": "haramball08"}, {"username": "gausal"}, {"username": "dianamirza"}, {"username": "maurijs"}]}